area_under_curve/__init__.py
area_under_curve/area_under_curve.py
area_under_curve-1.0.6.dist-info/LICENSE
area_under_curve-1.0.6.dist-info/METADATA
area_under_curve-1.0.6.dist-info/WHEEL
area_under_curve-1.0.6.dist-info/top_level.txt
area_under_curve-1.0.6.dist-info/RECORD
