Metadata-Version: 2.1
Name: area-under-curve
Version: 1.0.6
Summary: Calculate area under curve
Home-page: https://github.com/smycynek/area_under_curve
Author: Steven Mycynek
Author-email: sv@stevenvictor.net
License: MIT
Keywords: riemann-sum calculus
Platform: UNKNOWN
Classifier: Development Status :: 4 - Beta
Classifier: Intended Audience :: Developers
Classifier: License :: OSI Approved :: MIT License
Classifier: Programming Language :: Python :: 3
Classifier: Programming Language :: Python :: 3.7
Classifier: Programming Language :: Python :: 3.8
